elementz_querify/__init__.py
elementz_querify/querify.py
elementz_querify-1.0.16.dist-info/METADATA
elementz_querify-1.0.16.dist-info/WHEEL
elementz_querify-1.0.16.dist-info/top_level.txt
elementz_querify-1.0.16.dist-info/RECORD
